JwtRedirect/__init__.py
JwtRedirect/settings.py
JwtRedirect/views.py
JwtRedirect/templates/jwt-redirect-error.html
JwtRedirect/templates/redirect.html
jwt_redirect-0.2.5.dist-info/LICENSE
jwt_redirect-0.2.5.dist-info/METADATA
jwt_redirect-0.2.5.dist-info/WHEEL
jwt_redirect-0.2.5.dist-info/top_level.txt
jwt_redirect-0.2.5.dist-info/RECORD
