Metadata-Version: 2.1
Name: jwt-redirect
Version: 0.2.5
Summary: JWT Token login redirect
Home-page: UNKNOWN
Author: Xujia Li
Author-email: lixujiacn@outlook.com
License: UNKNOWN
Platform: UNKNOWN
Classifier: Programming Language :: Python :: 3
Classifier: License :: OSI Approved :: MIT License
Classifier: Operating System :: OS Independent
Requires-Python: >=3.6
Requires-Dist: Django
Requires-Dist: PyJWT
Requires-Dist: cryptography
